Metadata-Version: 2.1
Name: l2address
Version: 1.0.1
Summary: MAC address manipulation library
Home-page: https://github.com/EgorBlagov/l2address
Author: Egor Blagov
Author-email: e.m.blagov@gmail.com
License: MIT
Download-URL: https://github.com/EgorBlagov/l2address/archive/v1.0.1.tar.gz
Keywords: Networking,Telecommunication,MAC,L2
Platform: UNKNOWN
Classifier: Development Status :: 3 - Alpha
Classifier: Intended Audience :: Developers
Classifier: Topic :: Software Development :: Build Tools
Classifier: License :: OSI Approved :: MIT License
Classifier: Programming Language :: Python :: 3
Classifier: Programming Language :: Python :: 3.4
Classifier: Programming Language :: Python :: 3.5
Classifier: Programming Language :: Python :: 3.6
